MANIFEST.in
setup.py
probe/__init__.py
probe/log/__init__.py
probe/log/log.py
probe/log/cfg/logging.yml
probe_log.egg-info/PKG-INFO
probe_log.egg-info/SOURCES.txt
probe_log.egg-info/dependency_links.txt
probe_log.egg-info/entry_points.txt
probe_log.egg-info/namespace_packages.txt
probe_log.egg-info/pbr.json
probe_log.egg-info/requires.txt
probe_log.egg-info/top_level.txt
probe_log.egg-info/zip-safe