Metadata-Version: 1.0
Name: probe-log
Version: 0.0.4
Summary: logging utilities for probe projects
Home-page: UNKNOWN
Author: Petr Zikan
Author-email: zikan.p@gmail.com
License: GPLv3
Platform: UNKNOWN
